magnetismi/__init__.py
magnetismi/__main__.py
magnetismi/cli.py
magnetismi/magnetismi.py
magnetismi/model/__init__.py
magnetismi/model/cof.py
magnetismi/model/wmm-2020.txt
magnetismi/model/wmm-2020.txt.sha256
magnetismi/model/wmm-2020.txt.sha512
magnetismi-2022.10.9.dist-info/LICENSE
magnetismi-2022.10.9.dist-info/METADATA
magnetismi-2022.10.9.dist-info/WHEEL
magnetismi-2022.10.9.dist-info/entry_points.txt
magnetismi-2022.10.9.dist-info/top_level.txt
magnetismi-2022.10.9.dist-info/RECORD
