Metadata-Version: 2.1
Name: magnetismi
Version: 2022.10.9
Summary: Magnetism (Finnish: magnetismi) - another opinionated World Magnetic Model calculator.
Author-email: Stefan Hagen <stefan@hagen.link>
Maintainer-email: Stefan Hagen <stefan@hagen.link>
Project-URL: Homepage, https://git.sr.ht/~sthagen/magnetismi
Project-URL: Bug-Tracker, https://todo.sr.ht/~sthagen/magnetismi
Project-URL: Documentation, https://codes.dilettant.life/docs/magnetismi
Project-URL: Source-Code, https://git.sr.ht/~sthagen/magnetismi
Project-URL: Test-Coverage, https://codes.dilettant.life/coverage/magnetismi
Keywords: developer-tools
Classifier: Development Status :: 3 - Alpha
Classifier: Intended Audience :: Developers
Classifier: License :: OSI Approved :: MIT License
Classifier: Programming Language :: Python :: 3.8
Classifier: Programming Language :: Python :: 3.9
Classifier: Programming Language :: Python :: 3.10
Requires-Python: >=3.8
Provides-Extra: dev
License-File: LICENSE
